h5tui/__init__.py
h5tui/h5.py
h5tui/hdf5_tui.py
h5tui/hdf5_tui.tcss
h5tui/plugin.py
plugins/hex/__init__.py
plugins/image/__init__.py
h5ui-0.1.18.dist-info/METADATA
h5ui-0.1.18.dist-info/WHEEL
h5ui-0.1.18.dist-info/entry_points.txt
h5ui-0.1.18.dist-info/top_level.txt
h5ui-0.1.18.dist-info/RECORD
