Metadata-Version: 2.1
Name: h5ui
Version: 0.1.18
Summary: Terminal User interface for HDF5 file inspection.
Author-email: Rik Huygen <rik.huygen@kuleuven.be>
License: MIT Licence
Project-URL: repository, https://github.com/rhuygen/hdf5_ui
Keywords: HDF5,Terminal
Classifier: Development Status :: 4 - Beta
Classifier: Programming Language :: Python :: 3 :: Only
Classifier: License :: OSI Approved :: MIT License
Classifier: Operating System :: OS Independent
Requires-Python: >=3.8
Requires-Dist: textual
Requires-Dist: textual-imageview
Requires-Dist: textual-fspicker
Requires-Dist: h5py
Requires-Dist: pillow
Requires-Dist: natsort
Provides-Extra: dev
Requires-Dist: textual-dev ; extra == 'dev'
Provides-Extra: rel
Requires-Dist: build ; extra == 'rel'
Requires-Dist: twine ; extra == 'rel'
